Metadata-Version: 2.1
Name: pytest-xdist
Version: 3.6.0
Summary: pytest xdist plugin for distributed testing, most importantly across multiple CPUs
Author-email: holger krekel and contributors <pytest-dev@python.org>, holger@merlinux.eu
License: MIT License
Project-URL: Homepage, https://github.com/pytest-dev/pytest-xdist
Project-URL: Documentation, https://pytest-xdist.readthedocs.io/en/latest
Project-URL: Changelog, https://pytest-xdist.readthedocs.io/en/latest/changelog.html
Project-URL: Source, https://github.com/pytest-dev/pytest-xdist
Project-URL: Tracker, https://github.com/pytest-dev/pytest-xdist/issues
Platform: linux
Platform: osx
Platform: win32
Classifier: Development Status :: 5 - Production/Stable
Classifier: Framework :: Pytest
Classifier: Intended Audience :: Developers
Classifier: License :: OSI Approved :: MIT License
Classifier: Operating System :: POSIX
Classifier: Operating System :: Microsoft :: Windows
Classifier: Operating System :: MacOS :: MacOS X
Classifier: Topic :: Software Development :: Testing
Classifier: Topic :: Software Development :: Quality Assurance
Classifier: Topic :: Utilities
Classifier: Programming Language :: Python
Classifier: Programming Language :: Python :: 3
Classifier: Programming Language :: Python :: 3 :: Only
Classifier: Programming Language :: Python :: 3.8
Classifier: Programming Language :: Python :: 3.9
Classifier: Programming Language :: Python :: 3.10
Classifier: Programming Language :: Python :: 3.11
Classifier: Programming Language :: Python :: 3.12
Requires-Python: >=3.8
License-File: LICENSE
Requires-Dist: execnet>=2.1
Requires-Dist: pytest>=7.0.0
Provides-Extra: testing
Requires-Dist: filelock; extra == "testing"
Provides-Extra: psutil
Requires-Dist: psutil>=3.0; extra == "psutil"
Provides-Extra: setproctitle
Requires-Dist: setproctitle; extra == "setproctitle"
